{
  "results": [
    {
      "objectId": "KdGKMvW0G8",
      "Year": 2017,
      "Make": "Volvo",
      "Model": "XC60",
      "Category": "SUV",
      "createdAt": "2020-01-27T22:20:57.607Z",
      "updatedAt": "2020-01-27T22:20:57.607Z"
    },
    {
      "objectId": "4zzQXfMaFF",
      "Year": 2017,
      "Make": "Volvo",
      "Model": "V60",
      "Category": "Wagon",
      "createdAt": "2020-01-27T22:20:57.607Z",
      "updatedAt": "2020-01-27T22:20:57.607Z"
    },
    {
      "objectId": "ArwnBbRZMd",
      "Year": 2019,
      "Make": "Volvo",
      "Model": "XC90",
      "Category": "SUV2020",
      "field5": "Acura",
      "field6": "Integra",
      "field7": [
        "Sedan",
        "Hatchback"
      ],
      "createdAt": "2020-01-27T22:20:57.607Z",
      "updatedAt": "2020-01-27T22:20:57.607Z"
    },
    {
      "objectId": "Laa99UDGy2",
      "Year": 2018,
      "Make": "Volvo",
      "Model": "S90",
      "Category": "Sedan",
      "createdAt": "2020-01-27T22:20:57.607Z",
      "updatedAt": "2020-01-27T22:20:57.607Z"
    },
    {
      "objectId": "TUv4e7nPPQ",
      "Year": 2020,
      "Make": "Volvo",
      "Model": "XC40",
      "Category": "SUV",
      "createdAt": "2020-01-27T22:20:57.607Z",
      "updatedAt": "2020-01-27T22:20:57.607Z"
    },
    {
      "objectId": "RY1K9a0rBb",
      "Year": 2019,
      "Make": "Volvo",
      "Model": "S90",
      "Category": "Sedan",
      "createdAt": "2020-01-27T22:20:57.607Z",
      "updatedAt": "2020-01-27T22:20:57.607Z"
    },
    {
      "objectId": "QSJaxFN8Go",
      "Year": 2018,
      "Make": "Volvo",
      "Model": "V60",
      "Category": "Wagon",
      "createdAt": "2020-01-27T22:20:57.607Z",
      "updatedAt": "2020-01-27T22:20:57.607Z"
    },
    {
      "objectId": "ui3Iqs8WcG",
      "Year": 2017,
      "Make": "Volvo",
      "Model": "S60",
      "Category": "Sedan",
      "createdAt": "2020-01-27T22:20:57.607Z",
      "updatedAt": "2020-01-27T22:20:57.607Z"
    },
    {
      "objectId": "Hubsr9aiY0",
      "Year": 2016,
      "Make": "Volvo",
      "Model": "XC60",
      "Category": "SUV",
      "createdAt": "2020-01-27T22:20:57.607Z",
      "updatedAt": "2020-01-27T22:20:57.607Z"
    },
    {
      "objectId": "lY95LXpmuI",
      "Year": 2012,
      "Make": "Volvo",
      "Model": "C70",
      "Category": "Convertible",
      "createdAt": "2020-01-27T22:20:57.607Z",
      "updatedAt": "2020-01-27T22:20:57.607Z"
    },
    {
      "objectId": "iSr1NJQPMP",
      "Year": 2017,
      "Make": "Volvo",
      "Model": "S90",
      "Category": "Sedan",
      "createdAt": "2020-01-27T22:20:57.607Z",
      "updatedAt": "2020-01-27T22:20:57.607Z"
    },
    {
      "objectId": "8u1Ptb8B5T",
      "Year": 2013,
      "Make": "Volvo",
      "Model": "XC90",
      "Category": "SUV",
      "createdAt": "2020-01-27T22:20:57.607Z",
      "updatedAt": "2020-01-27T22:20:57.607Z"
    },
    {
      "objectId": "ChWF0TL2Oh",
      "Year": 2015,
      "Make": "Volvo",
      "Model": "V60",
      "Category": "Wagon",
      "createdAt": "2020-01-27T22:20:57.607Z",
      "updatedAt": "2020-01-27T22:20:57.607Z"
    },
    {
      "objectId": "Khj6dcKBbp",
      "Year": 2013,
      "Make": "Volvo",
      "Model": "C30",
      "Category": "Hatchback",
      "createdAt": "2020-01-27T22:20:57.607Z",
      "updatedAt": "2020-01-27T22:20:57.607Z"
    },
    {
      "objectId": "Y10bSNZNHC",
      "Year": 2014,
      "Make": "Volvo",
      "Model": "S80",
      "Category": "Sedan",
      "createdAt": "2020-01-27T22:20:57.607Z",
      "updatedAt": "2020-01-27T22:20:57.607Z"
    },
    {
      "objectId": "wzUXrORmFT",
      "Year": 2011,
      "Make": "Volvo",
      "Model": "S60",
      "Category": "Sedan",
      "createdAt": "2020-01-27T22:20:57.607Z",
      "updatedAt": "2020-01-27T22:20:57.607Z"
    },
    {
      "objectId": "JCqQwRSNDd",
      "Year": 2016,
      "Make": "Volvo",
      "Model": "S60",
      "Category": "Sedan",
      "createdAt": "2020-01-27T22:20:57.607Z",
      "updatedAt": "2020-01-27T22:20:57.607Z"
    },
    {
      "objectId": "0UIz1wim4j",
      "Year": 2018,
      "Make": "Volvo",
      "Model": "V90",
      "Category": "Wagon",
      "createdAt": "2020-01-27T22:20:57.607Z",
      "updatedAt": "2020-01-27T22:20:57.607Z"
    },
    {
      "objectId": "oS2hG1c7Gz",
      "Year": 2019,
      "Make": "Volvo",
      "Model": "XC60",
      "Category": "SUV",
      "createdAt": "2020-01-27T22:20:57.607Z",
      "updatedAt": "2020-01-27T22:20:57.607Z"
    },
    {
      "objectId": "AvKmQl4nt4",
      "Year": 2019,
      "Make": "Volvo",
      "Model": "V60",
      "Category": "Wagon",
      "createdAt": "2020-01-27T22:20:57.607Z",
      "updatedAt": "2020-01-27T22:20:57.607Z"
    },
    {
      "objectId": "2MUDl83I8i",
      "Year": 2018,
      "Make": "Volvo",
      "Model": "XC90",
      "Category": "SUV",
      "createdAt": "2020-01-27T22:20:57.607Z",
      "updatedAt": "2020-01-27T22:20:57.607Z"
    },
    {
      "objectId": "vE3fuhR2Jr",
      "Year": 2012,
      "Make": "Volvo",
      "Model": "C30",
      "Category": "Hatchback",
      "createdAt": "2020-01-27T22:20:57.607Z",
      "updatedAt": "2020-01-27T22:20:57.607Z"
    },
    {
      "objectId": "hL5grfpZDC",
      "Year": 2013,
      "Make": "Volvo",
      "Model": "S80",
      "Category": "Sedan",
      "createdAt": "2020-01-27T22:20:57.607Z",
      "updatedAt": "2020-01-27T22:20:57.607Z"
    },
    {
      "objectId": "GjQY5ppzEf",
      "Year": 2016,
      "Make": "Volvo",
      "Model": "V60",
      "Category": "Wagon",
      "createdAt": "2020-01-27T22:20:57.607Z",
      "updatedAt": "2020-01-27T22:20:57.607Z"
    },
    {
      "objectId": "nOOJUiaGfM",
      "Year": 2014,
      "Make": "Volvo",
      "Model": "XC90",
      "Category": "SUV",
      "createdAt": "2020-01-27T22:20:57.607Z",
      "updatedAt": "2020-01-27T22:20:57.607Z"
    },
    {
      "objectId": "W3Wkk0WF2K",
      "Year": 2013,
      "Make": "Volvo",
      "Model": "C70",
      "Category": "Convertible",
      "createdAt": "2020-01-27T22:20:57.607Z",
      "updatedAt": "2020-01-27T22:20:57.607Z"
    },
    {
      "objectId": "iCdUU8vdt9",
      "Year": 2011,
      "Make": "Volvo",
      "Model": "C70",
      "Category": "Convertible",
      "createdAt": "2020-01-27T22:20:57.607Z",
      "updatedAt": "2020-01-27T22:20:57.607Z"
    },
    {
      "objectId": "NT2vxSWm6o",
      "Year": 2010,
      "Make": "Volvo",
      "Model": "C30",
      "Category": "Hatchback",
      "createdAt": "2020-01-27T22:20:57.608Z",
      "updatedAt": "2020-01-27T22:20:57.608Z"
    },
    {
      "objectId": "TY7gBz3Z3n",
      "Year": 2008,
      "Make": "Volvo",
      "Model": "S40",
      "Category": "Sedan",
      "createdAt": "2020-01-27T22:20:57.608Z",
      "updatedAt": "2020-01-27T22:20:57.608Z"
    },
    {
      "objectId": "QwnOVfqiVL",
      "Year": 2010,
      "Make": "Volvo",
      "Model": "C70",
      "Category": "Convertible",
      "createdAt": "2020-01-27T22:20:57.608Z",
      "updatedAt": "2020-01-27T22:20:57.608Z"
    },
    {
      "objectId": "RLoclcxQGe",
      "Year": 2009,
      "Make": "Volvo",
      "Model": "C30",
      "Category": "Hatchback",
      "createdAt": "2020-01-27T22:20:57.608Z",
      "updatedAt": "2020-01-27T22:20:57.608Z"
    },
    {
      "objectId": "qBYAdFXtGq",
      "Year": 2010,
      "Make": "Volvo",
      "Model": "S80",
      "Category": "Sedan",
      "createdAt": "2020-01-27T22:20:57.608Z",
      "updatedAt": "2020-01-27T22:20:57.608Z"
    },
    {
      "objectId": "tMHFq4acST",
      "Year": 2009,
      "Make": "Volvo",
      "Model": "S60",
      "Category": "Sedan",
      "createdAt": "2020-01-27T22:20:57.608Z",
      "updatedAt": "2020-01-27T22:20:57.608Z"
    },
    {
      "objectId": "qfQd4cRsr5",
      "Year": 2008,
      "Make": "Volvo",
      "Model": "C30",
      "Category": "Hatchback",
      "createdAt": "2020-01-27T22:20:57.608Z",
      "updatedAt": "2020-01-27T22:20:57.608Z"
    },
    {
      "objectId": "Y5Db1dJdz9",
      "Year": 2008,
      "Make": "Volvo",
      "Model": "V70",
      "Category": "Wagon",
      "createdAt": "2020-01-27T22:20:57.608Z",
      "updatedAt": "2020-01-27T22:20:57.608Z"
    },
    {
      "objectId": "31Q1jbdqjr",
      "Year": 2006,
      "Make": "Volvo",
      "Model": "S80",
      "Category": "Sedan",
      "createdAt": "2020-01-27T22:20:57.608Z",
      "updatedAt": "2020-01-27T22:20:57.608Z"
    },
    {
      "objectId": "2nUSNAzfsX",
      "Year": 2016,
      "Make": "Volvo",
      "Model": "S80",
      "Category": "Sedan",
      "createdAt": "2020-01-27T22:20:57.607Z",
      "updatedAt": "2020-01-27T22:20:57.607Z"
    },
    {
      "objectId": "nvsk86n97h",
      "Year": 2019,
      "Make": "Volvo",
      "Model": "XC40",
      "Category": "SUV",
      "createdAt": "2020-01-27T22:20:57.607Z",
      "updatedAt": "2020-01-27T22:20:57.607Z"
    },
    {
      "objectId": "mwJVf6unoc",
      "Year": 2018,
      "Make": "Volvo",
      "Model": "S60",
      "Category": "Sedan",
      "createdAt": "2020-01-27T22:20:57.607Z",
      "updatedAt": "2020-01-27T22:20:57.607Z"
    },
    {
      "objectId": "qbyufsiIxy",
      "Year": 2019,
      "Make": "Volvo",
      "Model": "V90",
      "Category": "Wagon",
      "createdAt": "2020-01-27T22:20:57.607Z",
      "updatedAt": "2020-01-27T22:20:57.607Z"
    },
    {
      "objectId": "5NkobV4jU8",
      "Year": 2020,
      "Make": "Volvo",
      "Model": "XC60",
      "Category": "SUV",
      "createdAt": "2020-01-27T22:20:57.607Z",
      "updatedAt": "2020-01-27T22:20:57.607Z"
    },
    {
      "objectId": "cWNq3lfdqt",
      "Year": 2014,
      "Make": "Volvo",
      "Model": "S60",
      "Category": "Sedan",
      "createdAt": "2020-01-27T22:20:57.607Z",
      "updatedAt": "2020-01-27T22:20:57.607Z"
    },
    {
      "objectId": "UEGp7GLmjr",
      "Year": 2012,
      "Make": "Volvo",
      "Model": "S60",
      "Category": "Sedan",
      "createdAt": "2020-01-27T22:20:57.607Z",
      "updatedAt": "2020-01-27T22:20:57.607Z"
    },
    {
      "objectId": "D6QfvsBA6C",
      "Year": 2015,
      "Make": "Volvo",
      "Model": "XC70",
      "Category": "Wagon",
      "createdAt": "2020-01-27T22:20:57.607Z",
      "updatedAt": "2020-01-27T22:20:57.607Z"
    },
    {
      "objectId": "3IFGNTPDva",
      "Year": 2015,
      "Make": "Volvo",
      "Model": "S80",
      "Category": "Sedan",
      "createdAt": "2020-01-27T22:20:57.607Z",
      "updatedAt": "2020-01-27T22:20:57.607Z"
    },
    {
      "objectId": "EyGmkm4l9U",
      "Year": 2013,
      "Make": "Volvo",
      "Model": "S60",
      "Category": "Sedan",
      "createdAt": "2020-01-27T22:20:57.607Z",
      "updatedAt": "2020-01-27T22:20:57.607Z"
    },
    {
      "objectId": "FlyccyxdlQ",
      "Year": 2012,
      "Make": "Volvo",
      "Model": "XC60",
      "Category": "SUV",
      "createdAt": "2020-01-27T22:20:57.607Z",
      "updatedAt": "2020-01-27T22:20:57.607Z"
    },
    {
      "objectId": "OYmKAB63In",
      "Year": 2011,
      "Make": "Volvo",
      "Model": "S40",
      "Category": "Sedan",
      "createdAt": "2020-01-27T22:20:57.607Z",
      "updatedAt": "2020-01-27T22:20:57.607Z"
    },
    {
      "objectId": "yr38EIzioD",
      "Year": 2011,
      "Make": "Volvo",
      "Model": "XC60",
      "Category": "SUV",
      "createdAt": "2020-01-27T22:20:57.607Z",
      "updatedAt": "2020-01-27T22:20:57.607Z"
    },
    {
      "objectId": "4Nq6C8Mj8N",
      "Year": 2008,
      "Make": "Volvo",
      "Model": "XC70",
      "Category": "Wagon",
      "createdAt": "2020-01-27T22:20:57.608Z",
      "updatedAt": "2020-01-27T22:20:57.608Z"
    },
    {
      "objectId": "qO5YG9LF7I",
      "Year": 2010,
      "Make": "Volvo",
      "Model": "V50",
      "Category": "Wagon",
      "createdAt": "2020-01-27T22:20:57.608Z",
      "updatedAt": "2020-01-27T22:20:57.608Z"
    },
    {
      "objectId": "1uBkAWNmxw",
      "Year": 2009,
      "Make": "Volvo",
      "Model": "S40",
      "Category": "Sedan",
      "createdAt": "2020-01-27T22:20:57.608Z",
      "updatedAt": "2020-01-27T22:20:57.608Z"
    },
    {
      "objectId": "etwdcYT5sn",
      "Year": 2007,
      "Make": "Volvo",
      "Model": "S60",
      "Category": "Sedan",
      "createdAt": "2020-01-27T22:20:57.608Z",
      "updatedAt": "2020-01-27T22:20:57.608Z"
    },
    {
      "objectId": "tl9UJwcV1M",
      "Year": 2008,
      "Make": "Volvo",
      "Model": "V50",
      "Category": "Wagon",
      "createdAt": "2020-01-27T22:20:57.608Z",
      "updatedAt": "2020-01-27T22:20:57.608Z"
    },
    {
      "objectId": "te8UVM6LAu",
      "Year": 2008,
      "Make": "Volvo",
      "Model": "C70",
      "Category": "Convertible",
      "createdAt": "2020-01-27T22:20:57.608Z",
      "updatedAt": "2020-01-27T22:20:57.608Z"
    },
    {
      "objectId": "ySxIDambvD",
      "Year": 2007,
      "Make": "Volvo",
      "Model": "XC70",
      "Category": "Wagon",
      "createdAt": "2020-01-27T22:20:57.608Z",
      "updatedAt": "2020-01-27T22:20:57.608Z"
    },
    {
      "objectId": "Ypjh2CUkUB",
      "Year": 2017,
      "Make": "Volvo",
      "Model": "V90",
      "Category": "Wagon",
      "createdAt": "2020-01-27T22:20:57.607Z",
      "updatedAt": "2020-01-27T22:20:57.607Z"
    },
    {
      "objectId": "KDNHmfrQ7P",
      "Year": 2017,
      "Make": "Volvo",
      "Model": "XC90",
      "Category": "SUV",
      "createdAt": "2020-01-27T22:20:57.607Z",
      "updatedAt": "2020-01-27T22:20:57.607Z"
    },
    {
      "objectId": "I3DbTwaad5",
      "Year": 2020,
      "Make": "Volvo",
      "Model": "XC90",
      "Category": "SUV1992",
      "createdAt": "2020-01-27T22:20:57.607Z",
      "updatedAt": "2020-01-27T22:20:57.607Z"
    },
    {
      "objectId": "KsBs8h68rD",
      "Year": 2018,
      "Make": "Volvo",
      "Model": "XC60",
      "Category": "SUV",
      "createdAt": "2020-01-27T22:20:57.607Z",
      "updatedAt": "2020-01-27T22:20:57.607Z"
    },
    {
      "objectId": "0MdPKi7dhO",
      "Year": 2019,
      "Make": "Volvo",
      "Model": "S60",
      "Category": "Sedan",
      "createdAt": "2020-01-27T22:20:57.607Z",
      "updatedAt": "2020-01-27T22:20:57.607Z"
    },
    {
      "objectId": "36gDAEmQVL",
      "Year": 2015,
      "Make": "Volvo",
      "Model": "S60",
      "Category": "Sedan",
      "createdAt": "2020-01-27T22:20:57.607Z",
      "updatedAt": "2020-01-27T22:20:57.607Z"
    },
    {
      "objectId": "YSmtBDSxyu",
      "Year": 2014,
      "Make": "Volvo",
      "Model": "XC70",
      "Category": "Wagon",
      "createdAt": "2020-01-27T22:20:57.607Z",
      "updatedAt": "2020-01-27T22:20:57.607Z"
    },
    {
      "objectId": "Cahz7WmCIC",
      "Year": 2011,
      "Make": "Volvo",
      "Model": "C30",
      "Category": "Hatchback",
      "createdAt": "2020-01-27T22:20:57.607Z",
      "updatedAt": "2020-01-27T22:20:57.607Z"
    },
    {
      "objectId": "PXJBZEGHn3",
      "Year": 2012,
      "Make": "Volvo",
      "Model": "XC90",
      "Category": "SUV",
      "createdAt": "2020-01-27T22:20:57.607Z",
      "updatedAt": "2020-01-27T22:20:57.607Z"
    },
    {
      "objectId": "cbVm4FTQI7",
      "Year": 2014,
      "Make": "Volvo",
      "Model": "XC60",
      "Category": "SUV",
      "createdAt": "2020-01-27T22:20:57.607Z",
      "updatedAt": "2020-01-27T22:20:57.607Z"
    },
    {
      "objectId": "NRyakw0Cql",
      "Year": 2012,
      "Make": "Volvo",
      "Model": "S80",
      "Category": "Sedan",
      "createdAt": "2020-01-27T22:20:57.607Z",
      "updatedAt": "2020-01-27T22:20:57.607Z"
    },
    {
      "objectId": "k7Xa0bJpDC",
      "Year": 2009,
      "Make": "Volvo",
      "Model": "C70",
      "Category": "Convertible",
      "createdAt": "2020-01-27T22:20:57.608Z",
      "updatedAt": "2020-01-27T22:20:57.608Z"
    },
    {
      "objectId": "GCZG4utzoW",
      "Year": 2007,
      "Make": "Volvo",
      "Model": "S40",
      "Category": "Sedan",
      "createdAt": "2020-01-27T22:20:57.608Z",
      "updatedAt": "2020-01-27T22:20:57.608Z"
    },
    {
      "objectId": "8TgOXYWOvU",
      "Year": 2010,
      "Make": "Volvo",
      "Model": "XC70",
      "Category": "Wagon",
      "createdAt": "2020-01-27T22:20:57.608Z",
      "updatedAt": "2020-01-27T22:20:57.608Z"
    },
    {
      "objectId": "DRvFqWOUbQ",
      "Year": 2010,
      "Make": "Volvo",
      "Model": "XC60",
      "Category": "SUV",
      "createdAt": "2020-01-27T22:20:57.608Z",
      "updatedAt": "2020-01-27T22:20:57.608Z"
    },
    {
      "objectId": "irCdY8dXjG",
      "Year": 2006,
      "Make": "Volvo",
      "Model": "C70",
      "Category": "Convertible",
      "createdAt": "2020-01-27T22:20:57.608Z",
      "updatedAt": "2020-01-27T22:20:57.608Z"
    },
    {
      "objectId": "B4UbH28MJp",
      "Year": 2011,
      "Make": "Volvo",
      "Model": "S80",
      "Category": "Sedan",
      "createdAt": "2020-01-27T22:20:57.607Z",
      "updatedAt": "2020-01-27T22:20:57.607Z"
    },
    {
      "objectId": "W3OIuPC878",
      "Year": 2008,
      "Make": "Volvo",
      "Model": "S80",
      "Category": "Sedan",
      "createdAt": "2020-01-27T22:20:57.608Z",
      "updatedAt": "2020-01-27T22:20:57.608Z"
    },
    {
      "objectId": "QlDNS3m7oO",
      "Year": 2009,
      "Make": "Volvo",
      "Model": "XC70",
      "Category": "Wagon",
      "createdAt": "2020-01-27T22:20:57.608Z",
      "updatedAt": "2020-01-27T22:20:57.608Z"
    },
    {
      "objectId": "SPmGajK3OW",
      "Year": 2013,
      "Make": "Volvo",
      "Model": "XC70",
      "Category": "Wagon",
      "createdAt": "2020-01-27T22:20:57.607Z",
      "updatedAt": "2020-01-27T22:20:57.607Z"
    },
    {
      "objectId": "96d5FDG8yk",
      "Year": 2016,
      "Make": "Volvo",
      "Model": "XC70",
      "Category": "Wagon",
      "createdAt": "2020-01-27T22:20:57.607Z",
      "updatedAt": "2020-01-27T22:20:57.607Z"
    },
    {
      "objectId": "lSFtCpBFDD",
      "Year": 2013,
      "Make": "Volvo",
      "Model": "XC60",
      "Category": "SUV",
      "createdAt": "2020-01-27T22:20:57.607Z",
      "updatedAt": "2020-01-27T22:20:57.607Z"
    },
    {
      "objectId": "NJoC0SDYFy",
      "Year": 2015,
      "Make": "Volvo",
      "Model": "XC60",
      "Category": "SUV",
      "createdAt": "2020-01-27T22:20:57.607Z",
      "updatedAt": "2020-01-27T22:20:57.607Z"
    },
    {
      "objectId": "v5TYeXXiGI",
      "Year": 2016,
      "Make": "Volvo",
      "Model": "XC90",
      "Category": "SUV",
      "createdAt": "2020-01-27T22:20:57.607Z",
      "updatedAt": "2020-01-27T22:20:57.607Z"
    },
    {
      "objectId": "IvKeHGncnZ",
      "Year": 2011,
      "Make": "Volvo",
      "Model": "XC70",
      "Category": "Wagon",
      "createdAt": "2020-01-27T22:20:57.607Z",
      "updatedAt": "2020-01-27T22:20:57.607Z"
    },
    {
      "objectId": "IoC7jQtiPo",
      "Year": 2009,
      "Make": "Volvo",
      "Model": "S80",
      "Category": "Sedan",
      "createdAt": "2020-01-27T22:20:57.608Z",
      "updatedAt": "2020-01-27T22:20:57.608Z"
    },
    {
      "objectId": "xdJEGqZRqi",
      "Year": 2012,
      "Make": "Volvo",
      "Model": "XC70",
      "Category": "Wagon",
      "createdAt": "2020-01-27T22:20:57.607Z",
      "updatedAt": "2020-01-27T22:20:57.607Z"
    },
    {
      "objectId": "G4FBwwah6S",
      "Year": 2010,
      "Make": "Volvo",
      "Model": "V70",
      "Category": "Wagon",
      "createdAt": "2020-01-27T22:20:57.608Z",
      "updatedAt": "2020-01-27T22:20:57.608Z"
    },
    {
      "objectId": "Q5AU9rvIIU",
      "Year": 2011,
      "Make": "Volvo",
      "Model": "XC90",
      "Category": "SUV",
      "createdAt": "2020-01-27T22:20:57.608Z",
      "updatedAt": "2020-01-27T22:20:57.608Z"
    },
    {
      "objectId": "CoxFem8EuO",
      "Year": 2007,
      "Make": "Volvo",
      "Model": "S80",
      "Category": "Sedan",
      "createdAt": "2020-01-27T22:20:57.608Z",
      "updatedAt": "2020-01-27T22:20:57.608Z"
    },
    {
      "objectId": "0H05cg7DH0",
      "Year": 2006,
      "Make": "Volvo",
      "Model": "V50",
      "Category": "Wagon",
      "createdAt": "2020-01-27T22:20:57.608Z",
      "updatedAt": "2020-01-27T22:20:57.608Z"
    },
    {
      "objectId": "mqWiZCbA4l",
      "Year": 2007,
      "Make": "Volvo",
      "Model": "V70",
      "Category": "Wagon",
      "createdAt": "2020-01-27T22:20:57.608Z",
      "updatedAt": "2020-01-27T22:20:57.608Z"
    },
    {
      "objectId": "Sb4sJ0DXtC",
      "Year": 2009,
      "Make": "Volvo",
      "Model": "XC90",
      "Category": "SUV",
      "createdAt": "2020-01-27T22:20:57.608Z",
      "updatedAt": "2020-01-27T22:20:57.608Z"
    },
    {
      "objectId": "ynqDV3UBGa",
      "Year": 2008,
      "Make": "Volvo",
      "Model": "XC90",
      "Category": "SUV",
      "createdAt": "2020-01-27T22:20:57.608Z",
      "updatedAt": "2020-01-27T22:20:57.608Z"
    },
    {
      "objectId": "RftcShQuRH",
      "Year": 2006,
      "Make": "Volvo",
      "Model": "S60",
      "Category": "Sedan",
      "createdAt": "2020-01-27T22:20:57.608Z",
      "updatedAt": "2020-01-27T22:20:57.608Z"
    },
    {
      "objectId": "n4FfccdgFP",
      "Year": 2009,
      "Make": "Volvo",
      "Model": "V70",
      "Category": "Wagon",
      "createdAt": "2020-01-27T22:20:57.608Z",
      "updatedAt": "2020-01-27T22:20:57.608Z"
    },
    {
      "objectId": "2daks9ttLx",
      "Year": 2009,
      "Make": "Volvo",
      "Model": "V50",
      "Category": "Wagon",
      "createdAt": "2020-01-27T22:20:57.608Z",
      "updatedAt": "2020-01-27T22:20:57.608Z"
    },
    {
      "objectId": "0fMSOPRXms",
      "Year": 2010,
      "Make": "Volvo",
      "Model": "XC90",
      "Category": "SUV",
      "createdAt": "2020-01-27T22:20:57.608Z",
      "updatedAt": "2020-01-27T22:20:57.608Z"
    },
    {
      "objectId": "T7DTqFf11I",
      "Year": 2011,
      "Make": "Volvo",
      "Model": "V50",
      "Category": "Wagon",
      "createdAt": "2020-01-27T22:20:57.607Z",
      "updatedAt": "2020-01-27T22:20:57.607Z"
    },
    {
      "objectId": "WNWQ65RMDq",
      "Year": 2010,
      "Make": "Volvo",
      "Model": "S40",
      "Category": "Sedan",
      "createdAt": "2020-01-27T22:20:57.608Z",
      "updatedAt": "2020-01-27T22:20:57.608Z"
    },
    {
      "objectId": "6gMutw8nZS",
      "Year": 2008,
      "Make": "Volvo",
      "Model": "S60",
      "Category": "Sedan",
      "createdAt": "2020-01-27T22:20:57.608Z",
      "updatedAt": "2020-01-27T22:20:57.608Z"
    },
    {
      "objectId": "66qSOny1Pv",
      "Year": 2007,
      "Make": "Volvo",
      "Model": "C70",
      "Category": "Convertible",
      "createdAt": "2020-01-27T22:20:57.608Z",
      "updatedAt": "2020-01-27T22:20:57.608Z"
    },
    {
      "objectId": "EEkHCa4oCn",
      "Year": 2007,
      "Make": "Volvo",
      "Model": "XC90",
      "Category": "SUV",
      "createdAt": "2020-01-27T22:20:57.608Z",
      "updatedAt": "2020-01-27T22:20:57.608Z"
    },
    {
      "objectId": "UlcGIdAG6k",
      "Year": 2007,
      "Make": "Volvo",
      "Model": "V50",
      "Category": "Wagon",
      "createdAt": "2020-01-27T22:20:57.608Z",
      "updatedAt": "2020-01-27T22:20:57.608Z"
    },
    {
      "objectId": "E22m6NoqAi",
      "Year": 2006,
      "Make": "Volvo",
      "Model": "S40",
      "Category": "Sedan",
      "createdAt": "2020-01-27T22:20:57.608Z",
      "updatedAt": "2020-01-27T22:20:57.608Z"
    },
    {
      "objectId": "E2W7fSYwEk",
      "Year": 2005,
      "Make": "Volvo",
      "Model": "S40",
      "Category": "Sedan",
      "createdAt": "2020-01-27T22:20:58.473Z",
      "updatedAt": "2020-01-27T22:20:58.473Z"
    },
    {
      "objectId": "s7aYljpZsV",
      "Year": 2006,
      "Make": "Volvo",
      "Model": "XC90",
      "Category": "SUV",
      "createdAt": "2020-01-27T22:20:58.473Z",
      "updatedAt": "2020-01-27T22:20:58.473Z"
    },
    {
      "objectId": "xvky3HXzhz",
      "Year": 2005,
      "Make": "Volvo",
      "Model": "S60",
      "Category": "Sedan",
      "createdAt": "2020-01-27T22:20:58.473Z",
      "updatedAt": "2020-01-27T22:20:58.473Z"
    },
    {
      "objectId": "f1Zd7etF0I",
      "Year": 2006,
      "Make": "Volvo",
      "Model": "V70",
      "Category": "Wagon",
      "createdAt": "2020-01-27T22:20:58.473Z",
      "updatedAt": "2020-01-27T22:20:58.473Z"
    },
    {
      "objectId": "vFJzG0NtBa",
      "Year": 2006,
      "Make": "Volvo",
      "Model": "XC70",
      "Category": "Wagon",
      "createdAt": "2020-01-27T22:20:58.473Z",
      "updatedAt": "2020-01-27T22:20:58.473Z"
    },
    {
      "objectId": "FkwW7ilLZ1",
      "Year": 2005,
      "Make": "Volvo",
      "Model": "V50",
      "Category": "Wagon",
      "createdAt": "2020-01-27T22:20:58.473Z",
      "updatedAt": "2020-01-27T22:20:58.473Z"
    },
    {
      "objectId": "kRzKi7jyA5",
      "Year": 2005,
      "Make": "Volvo",
      "Model": "S80",
      "Category": "Sedan",
      "createdAt": "2020-01-27T22:20:58.473Z",
      "updatedAt": "2020-01-27T22:20:58.473Z"
    },
    {
      "objectId": "jnyFkH5QUC",
      "Year": 2005,
      "Make": "Volvo",
      "Model": "XC70",
      "Category": "Wagon",
      "createdAt": "2020-01-27T22:20:58.473Z",
      "updatedAt": "2020-01-27T22:20:58.473Z"
    },
    {
      "objectId": "FUQuCpRc7z",
      "Year": 2005,
      "Make": "Volvo",
      "Model": "XC90",
      "Category": "SUV",
      "createdAt": "2020-01-27T22:20:58.473Z",
      "updatedAt": "2020-01-27T22:20:58.473Z"
    },
    {
      "objectId": "7nIGSRamHb",
      "Year": 2005,
      "Make": "Volvo",
      "Model": "V70",
      "Category": "Wagon",
      "createdAt": "2020-01-27T22:20:58.473Z",
      "updatedAt": "2020-01-27T22:20:58.473Z"
    },
    {
      "objectId": "8zkM1oA4yN",
      "Year": 2004,
      "Make": "Volvo",
      "Model": "S60",
      "Category": "Sedan",
      "createdAt": "2020-01-27T22:20:58.473Z",
      "updatedAt": "2020-01-27T22:20:58.473Z"
    },
    {
      "objectId": "8FnjbVbd2r",
      "Year": 2004,
      "Make": "Volvo",
      "Model": "C70",
      "Category": "Convertible",
      "createdAt": "2020-01-27T22:20:58.473Z",
      "updatedAt": "2020-01-27T22:20:58.473Z"
    },
    {
      "objectId": "K7wEntIuDG",
      "Year": 2004,
      "Make": "Volvo",
      "Model": "S80",
      "Category": "Sedan",
      "createdAt": "2020-01-27T22:20:58.473Z",
      "updatedAt": "2020-01-27T22:20:58.473Z"
    },
    {
      "objectId": "s2upSoZNFO",
      "Year": 2004,
      "Make": "Volvo",
      "Model": "S40",
      "Category": "Sedan",
      "createdAt": "2020-01-27T22:20:58.473Z",
      "updatedAt": "2020-01-27T22:20:58.473Z"
    },
    {
      "objectId": "wfl9QM7U4x",
      "Year": 2004,
      "Make": "Volvo",
      "Model": "S40 (New)",
      "Category": "Sedan",
      "createdAt": "2020-01-27T22:20:58.473Z",
      "updatedAt": "2020-01-27T22:20:58.473Z"
    },
    {
      "objectId": "ZUB4uGX9Wn",
      "Year": 2004,
      "Make": "Volvo",
      "Model": "XC70",
      "Category": "Wagon",
      "createdAt": "2020-01-27T22:20:58.473Z",
      "updatedAt": "2020-01-27T22:20:58.473Z"
    },
    {
      "objectId": "RKiNEOAh0W",
      "Year": 2003,
      "Make": "Volvo",
      "Model": "C70",
      "Category": "Convertible",
      "createdAt": "2020-01-27T22:20:58.473Z",
      "updatedAt": "2020-01-27T22:20:58.473Z"
    },
    {
      "objectId": "uT9V3GHNUV",
      "Year": 2004,
      "Make": "Volvo",
      "Model": "V70",
      "Category": "Wagon",
      "createdAt": "2020-01-27T22:20:58.473Z",
      "updatedAt": "2020-01-27T22:20:58.473Z"
    },
    {
      "objectId": "pMEp0EMexh",
      "Year": 2004,
      "Make": "Volvo",
      "Model": "V40",
      "Category": "Wagon",
      "createdAt": "2020-01-27T22:20:58.473Z",
      "updatedAt": "2020-01-27T22:20:58.473Z"
    },
    {
      "objectId": "hlff3cboup",
      "Year": 2004,
      "Make": "Volvo",
      "Model": "XC90",
      "Category": "SUV",
      "createdAt": "2020-01-27T22:20:58.473Z",
      "updatedAt": "2020-01-27T22:20:58.473Z"
    },
    {
      "objectId": "XVUYGZSONx",
      "Year": 2003,
      "Make": "Volvo",
      "Model": "S80",
      "Category": "Sedan",
      "createdAt": "2020-01-27T22:20:58.473Z",
      "updatedAt": "2020-01-27T22:20:58.473Z"
    },
    {
      "objectId": "o1PIYYCUkh",
      "Year": 2003,
      "Make": "Volvo",
      "Model": "V40",
      "Category": "Wagon",
      "createdAt": "2020-01-27T22:20:58.473Z",
      "updatedAt": "2020-01-27T22:20:58.473Z"
    },
    {
      "objectId": "E5pD76SlmD",
      "Year": 2003,
      "Make": "Volvo",
      "Model": "S40",
      "Category": "Sedan",
      "createdAt": "2020-01-27T22:20:58.473Z",
      "updatedAt": "2020-01-27T22:20:58.473Z"
    },
    {
      "objectId": "6T3D3LFNfl",
      "Year": 2003,
      "Make": "Volvo",
      "Model": "V70",
      "Category": "Wagon",
      "createdAt": "2020-01-27T22:20:58.473Z",
      "updatedAt": "2020-01-27T22:20:58.473Z"
    },
    {
      "objectId": "gtiAcLRp9d",
      "Year": 2003,
      "Make": "Volvo",
      "Model": "S60",
      "Category": "Sedan",
      "createdAt": "2020-01-27T22:20:58.473Z",
      "updatedAt": "2020-01-27T22:20:58.473Z"
    },
    {
      "objectId": "AKJaeUEGCK",
      "Year": 2003,
      "Make": "Volvo",
      "Model": "XC70",
      "Category": "Wagon",
      "createdAt": "2020-01-27T22:20:58.473Z",
      "updatedAt": "2020-01-27T22:20:58.473Z"
    },
    {
      "objectId": "Y5SZ6ID8hE",
      "Year": 2002,
      "Make": "Volvo",
      "Model": "S60",
      "Category": "Sedan",
      "createdAt": "2020-01-27T22:20:58.474Z",
      "updatedAt": "2020-01-27T22:20:58.474Z"
    },
    {
      "objectId": "VFzyno1qGc",
      "Year": 2003,
      "Make": "Volvo",
      "Model": "XC90",
      "Category": "SUV",
      "createdAt": "2020-01-27T22:20:58.473Z",
      "updatedAt": "2020-01-27T22:20:58.473Z"
    },
    {
      "objectId": "PwBm3kld9p",
      "Year": 2002,
      "Make": "Volvo",
      "Model": "C70",
      "Category": "Convertible, Coupe",
      "createdAt": "2020-01-27T22:20:58.473Z",
      "updatedAt": "2020-01-27T22:20:58.473Z"
    },
    {
      "objectId": "KrqQQEuFFX",
      "Year": 2002,
      "Make": "Volvo",
      "Model": "S40",
      "Category": "Sedan",
      "createdAt": "2020-01-27T22:20:58.473Z",
      "updatedAt": "2020-01-27T22:20:58.473Z"
    },
    {
      "objectId": "Ooc0yNcPLW",
      "Year": 2002,
      "Make": "Volvo",
      "Model": "S80",
      "Category": "Sedan",
      "createdAt": "2020-01-27T22:20:58.474Z",
      "updatedAt": "2020-01-27T22:20:58.474Z"
    },
    {
      "objectId": "mOwOJ2lAlO",
      "Year": 2002,
      "Make": "Volvo",
      "Model": "V70",
      "Category": "Wagon",
      "createdAt": "2020-01-27T22:20:58.474Z",
      "updatedAt": "2020-01-27T22:20:58.474Z"
    },
    {
      "objectId": "IKQqKnZv4w",
      "Year": 2001,
      "Make": "Volvo",
      "Model": "C70",
      "Category": "Convertible, Coupe",
      "createdAt": "2020-01-27T22:20:58.474Z",
      "updatedAt": "2020-01-27T22:20:58.474Z"
    },
    {
      "objectId": "mbUIERqQ8z",
      "Year": 2002,
      "Make": "Volvo",
      "Model": "V40",
      "Category": "Wagon",
      "createdAt": "2020-01-27T22:20:58.474Z",
      "updatedAt": "2020-01-27T22:20:58.474Z"
    },
    {
      "objectId": "9JXu6y2pHD",
      "Year": 2001,
      "Make": "Volvo",
      "Model": "S40",
      "Category": "Sedan",
      "createdAt": "2020-01-27T22:20:58.474Z",
      "updatedAt": "2020-01-27T22:20:58.474Z"
    },
    {
      "objectId": "Yd6xr1rdsQ",
      "Year": 2000,
      "Make": "Volvo",
      "Model": "C70",
      "Category": "Coupe, Convertible",
      "createdAt": "2020-01-27T22:20:58.474Z",
      "updatedAt": "2020-01-27T22:20:58.474Z"
    },
    {
      "objectId": "gOkAL16xRr",
      "Year": 2001,
      "Make": "Volvo",
      "Model": "S60",
      "Category": "Sedan",
      "createdAt": "2020-01-27T22:20:58.474Z",
      "updatedAt": "2020-01-27T22:20:58.474Z"
    },
    {
      "objectId": "lCgRIoy7TE",
      "Year": 2001,
      "Make": "Volvo",
      "Model": "V40",
      "Category": "Wagon",
      "createdAt": "2020-01-27T22:20:58.474Z",
      "updatedAt": "2020-01-27T22:20:58.474Z"
    },
    {
      "objectId": "5ncb2V5dgJ",
      "Year": 2001,
      "Make": "Volvo",
      "Model": "S80",
      "Category": "Sedan",
      "createdAt": "2020-01-27T22:20:58.474Z",
      "updatedAt": "2020-01-27T22:20:58.474Z"
    },
    {
      "objectId": "VkOt9RUwPV",
      "Year": 2001,
      "Make": "Volvo",
      "Model": "V70",
      "Category": "Wagon",
      "createdAt": "2020-01-27T22:20:58.474Z",
      "updatedAt": "2020-01-27T22:20:58.474Z"
    },
    {
      "objectId": "NIS5V3k9PL",
      "Year": 2000,
      "Make": "Volvo",
      "Model": "S40",
      "Category": "Sedan",
      "createdAt": "2020-01-27T22:20:58.474Z",
      "updatedAt": "2020-01-27T22:20:58.474Z"
    },
    {
      "objectId": "mdiOZJA11x",
      "Year": 2000,
      "Make": "Volvo",
      "Model": "V40",
      "Category": "Wagon",
      "createdAt": "2020-01-27T22:20:58.474Z",
      "updatedAt": "2020-01-27T22:20:58.474Z"
    },
    {
      "objectId": "mgOJuq5tND",
      "Year": 2000,
      "Make": "Volvo",
      "Model": "S70",
      "Category": "Sedan",
      "createdAt": "2020-01-27T22:20:58.474Z",
      "updatedAt": "2020-01-27T22:20:58.474Z"
    },
    {
      "objectId": "y3SPDGSLk5",
      "Year": 2000,
      "Make": "Volvo",
      "Model": "S80",
      "Category": "Sedan",
      "createdAt": "2020-01-27T22:20:58.474Z",
      "updatedAt": "2020-01-27T22:20:58.474Z"
    },
    {
      "objectId": "9N3esRwWkF",
      "Year": 2000,
      "Make": "Volvo",
      "Model": "V70",
      "Category": "Wagon",
      "createdAt": "2020-01-27T22:20:58.474Z",
      "updatedAt": "2020-01-27T22:20:58.474Z"
    },
    {
      "objectId": "lFK623BJxl",
      "Year": 1999,
      "Make": "Volvo",
      "Model": "S70",
      "Category": "Sedan",
      "createdAt": "2020-01-27T22:20:58.474Z",
      "updatedAt": "2020-01-27T22:20:58.474Z"
    },
    {
      "objectId": "dYsdqHEiYJ",
      "Year": 1999,
      "Make": "Volvo",
      "Model": "C70",
      "Category": "Coupe, Convertible",
      "createdAt": "2020-01-27T22:20:58.474Z",
      "updatedAt": "2020-01-27T22:20:58.474Z"
    },
    {
      "objectId": "twNTEleu1L",
      "Year": 1998,
      "Make": "Volvo",
      "Model": "C70",
      "Category": "Coupe, Convertible",
      "createdAt": "2020-01-27T22:20:58.474Z",
      "updatedAt": "2020-01-27T22:20:58.474Z"
    },
    {
      "objectId": "iWTlnJWAo5",
      "Year": 1999,
      "Make": "Volvo",
      "Model": "S80",
      "Category": "Sedan",
      "createdAt": "2020-01-27T22:20:58.474Z",
      "updatedAt": "2020-01-27T22:20:58.474Z"
    },
    {
      "objectId": "nUjCf4FxDC",
      "Year": 1999,
      "Make": "Volvo",
      "Model": "V70",
      "Category": "Wagon",
      "createdAt": "2020-01-27T22:20:58.474Z",
      "updatedAt": "2020-01-27T22:20:58.474Z"
    },
    {
      "objectId": "BCBV8HQCA9",
      "Year": 1998,
      "Make": "Volvo",
      "Model": "S90",
      "Category": "Sedan",
      "createdAt": "2020-01-27T22:20:58.474Z",
      "updatedAt": "2020-01-27T22:20:58.474Z"
    },
    {
      "objectId": "EszP4k5Cpc",
      "Year": 1998,
      "Make": "Volvo",
      "Model": "V70",
      "Category": "Wagon",
      "createdAt": "2020-01-27T22:20:58.474Z",
      "updatedAt": "2020-01-27T22:20:58.474Z"
    },
    {
      "objectId": "Th4WOZBF1g",
      "Year": 1998,
      "Make": "Volvo",
      "Model": "S70",
      "Category": "Sedan",
      "createdAt": "2020-01-27T22:20:58.474Z",
      "updatedAt": "2020-01-27T22:20:58.474Z"
    },
    {
      "objectId": "3Ed4BpHZHu",
      "Year": 1998,
      "Make": "Volvo",
      "Model": "V90",
      "Category": "Wagon",
      "createdAt": "2020-01-27T22:20:58.474Z",
      "updatedAt": "2020-01-27T22:20:58.474Z"
    },
    {
      "objectId": "CrAE6AH91s",
      "Year": 1997,
      "Make": "Volvo",
      "Model": "850",
      "Category": "Sedan, Wagon",
      "createdAt": "2020-01-27T22:20:58.474Z",
      "updatedAt": "2020-01-27T22:20:58.474Z"
    },
    {
      "objectId": "Ok2AoMZGGW",
      "Year": 1996,
      "Make": "Volvo",
      "Model": "960",
      "Category": "Sedan, Wagon",
      "createdAt": "2020-01-27T22:20:58.474Z",
      "updatedAt": "2020-01-27T22:20:58.474Z"
    },
    {
      "objectId": "ZBHeBhpS2D",
      "Year": 1997,
      "Make": "Volvo",
      "Model": "960",
      "Category": "Sedan, Wagon",
      "createdAt": "2020-01-27T22:20:58.474Z",
      "updatedAt": "2020-01-27T22:20:58.474Z"
    },
    {
      "objectId": "7axQl5oFVz",
      "Year": 1997,
      "Make": "Volvo",
      "Model": "S90",
      "Category": "Sedan",
      "createdAt": "2020-01-27T22:20:58.474Z",
      "updatedAt": "2020-01-27T22:20:58.474Z"
    },
    {
      "objectId": "WyCZ0183Sf",
      "Year": 1996,
      "Make": "Volvo",
      "Model": "850",
      "Category": "Wagon, Sedan",
      "createdAt": "2020-01-27T22:20:58.474Z",
      "updatedAt": "2020-01-27T22:20:58.474Z"
    },
    {
      "objectId": "UInv0DfVC8",
      "Year": 1997,
      "Make": "Volvo",
      "Model": "V90",
      "Category": "Wagon",
      "createdAt": "2020-01-27T22:20:58.474Z",
      "updatedAt": "2020-01-27T22:20:58.474Z"
    },
    {
      "objectId": "zfpJCAzOGU",
      "Year": 1994,
      "Make": "Volvo",
      "Model": "940",
      "Category": "Sedan, Wagon",
      "createdAt": "2020-01-27T22:20:58.474Z",
      "updatedAt": "2020-01-27T22:20:58.474Z"
    },
    {
      "objectId": "8F85lzkqDX",
      "Year": 1994,
      "Make": "Volvo",
      "Model": "850",
      "Category": "Wagon, Sedan",
      "createdAt": "2020-01-27T22:20:58.474Z",
      "updatedAt": "2020-01-27T22:20:58.474Z"
    },
    {
      "objectId": "33Kkd2thQQ",
      "Year": 1995,
      "Make": "Volvo",
      "Model": "850",
      "Category": "Wagon, Sedan",
      "createdAt": "2020-01-27T22:20:58.474Z",
      "updatedAt": "2020-01-27T22:20:58.474Z"
    },
    {
      "objectId": "FdH5iddm1G",
      "Year": 1995,
      "Make": "Volvo",
      "Model": "940",
      "Category": "Sedan, Wagon",
      "createdAt": "2020-01-27T22:20:58.474Z",
      "updatedAt": "2020-01-27T22:20:58.474Z"
    },
    {
      "objectId": "bX4Ud8xPYz",
      "Year": 1995,
      "Make": "Volvo",
      "Model": "960",
      "Category": "Sedan, Wagon",
      "createdAt": "2020-01-27T22:20:58.474Z",
      "updatedAt": "2020-01-27T22:20:58.474Z"
    },
    {
      "objectId": "3rEfRaiU67",
      "Year": 1993,
      "Make": "Volvo",
      "Model": "940",
      "Category": "Sedan, Wagon",
      "createdAt": "2020-01-27T22:20:58.474Z",
      "updatedAt": "2020-01-27T22:20:58.474Z"
    },
    {
      "objectId": "IVuvQ9arAD",
      "Year": 1993,
      "Make": "Volvo",
      "Model": "240",
      "Category": "Sedan, Wagon",
      "createdAt": "2020-01-27T22:20:58.474Z",
      "updatedAt": "2020-01-27T22:20:58.474Z"
    },
    {
      "objectId": "3A9bI3LXwU",
      "Year": 1994,
      "Make": "Volvo",
      "Model": "960",
      "Category": "Sedan, Wagon",
      "createdAt": "2020-01-27T22:20:58.474Z",
      "updatedAt": "2020-01-27T22:20:58.474Z"
    },
    {
      "objectId": "InVl9sJ5uB",
      "Year": 1993,
      "Make": "Volvo",
      "Model": "850",
      "Category": "Sedan",
      "createdAt": "2020-01-27T22:20:58.474Z",
      "updatedAt": "2020-01-27T22:20:58.474Z"
    },
    {
      "objectId": "mj5K4BsPzm",
      "Year": 1993,
      "Make": "Volvo",
      "Model": "960",
      "Category": "Sedan, Wagon",
      "createdAt": "2020-01-27T22:20:58.474Z",
      "updatedAt": "2020-01-27T22:20:58.474Z"
    },
    {
      "objectId": "irinjs73XZ",
      "Year": 1992,
      "Make": "Volvo",
      "Model": "940",
      "Category": "Sedan, Wagon",
      "createdAt": "2020-01-27T22:20:58.474Z",
      "updatedAt": "2020-01-27T22:20:58.474Z"
    },
    {
      "objectId": "dOgwEro1TH",
      "Year": 1992,
      "Make": "Volvo",
      "Model": "240",
      "Category": "Wagon, Sedan",
      "createdAt": "2020-01-27T22:20:58.474Z",
      "updatedAt": "2020-01-27T22:20:58.474Z"
    },
    {
      "objectId": "5FtUDEM6qN",
      "Year": 1992,
      "Make": "Volvo",
      "Model": "960",
      "Category": "Sedan, Wagon",
      "createdAt": "2020-01-27T22:20:58.474Z",
      "updatedAt": "2020-01-27T22:20:58.474Z"
    },
    {
      "objectId": "MvxHFirG6J",
      "Year": 1992,
      "Make": "Volvo",
      "Model": "740",
      "Category": "Wagon, Sedan",
      "createdAt": "2020-01-27T22:20:58.474Z",
      "updatedAt": "2020-01-27T22:20:58.474Z"
    },
    {
      "objectId": "FJx3ZAZQtW",
      "Year": 2021,
      "Make": "Volvo",
      "Model": "S90",
      "Category": "Sedan",
      "createdAt": "2021-04-15T13:37:07.621Z",
      "updatedAt": "2021-04-15T13:37:07.621Z"
    },
    {
      "objectId": "RDdw85EfDl",
      "Year": 2021,
      "Make": "Volvo",
      "Model": "V60",
      "Category": "Wagon",
      "createdAt": "2021-04-15T13:37:07.621Z",
      "updatedAt": "2021-04-15T13:37:07.621Z"
    },
    {
      "objectId": "2haVrBoAXy",
      "Year": 2021,
      "Make": "Volvo",
      "Model": "V90",
      "Category": "Wagon",
      "createdAt": "2021-04-15T13:37:07.621Z",
      "updatedAt": "2021-04-15T13:37:07.621Z"
    },
    {
      "objectId": "KLbHqB6ddc",
      "Year": 2021,
      "Make": "Volvo",
      "Model": "XC60",
      "Category": "SUV",
      "createdAt": "2021-04-15T13:37:07.621Z",
      "updatedAt": "2021-04-15T13:37:07.621Z"
    },
    {
      "objectId": "pw2omtKIub",
      "Year": 2021,
      "Make": "Volvo",
      "Model": "XC40",
      "Category": "SUV",
      "createdAt": "2021-04-15T13:37:07.621Z",
      "updatedAt": "2021-04-15T13:37:07.621Z"
    },
    {
      "objectId": "AxjSADxkE0",
      "Year": 2021,
      "Make": "Volvo",
      "Model": "XC90",
      "Category": "SUV",
      "createdAt": "2021-04-15T13:37:07.621Z",
      "updatedAt": "2021-04-15T13:37:07.621Z"
    }
  ]
}